muoblp/__init__.py
muoblp/model/__init__.py
muoblp/model/multi_objective_lp.py
muoblp/utils/__init__.py
muoblp/utils/lpReaderUtils.py
muoblp/utils/lpWriterUtils.py
muoblp/utils/utils.py
muoblp-1.0.2.dist-info/METADATA
muoblp-1.0.2.dist-info/WHEEL
muoblp-1.0.2.dist-info/RECORD
